Metadata-Version: 2.1
Name: cicd-test
Version: 3.10.5
Summary: CICD pipeline tests
Home-page: https://github.com/chuckorde/cicd-test
Author: Chuck Orde
Author-email: chuckorde@gmail.com
License: BSD-3-Clause
Download-URL: https://github.com/chuckorde/cicd-test/archive/v3.10.5/.tar.gz
Platform: UNKNOWN
Classifier: Development Status :: 3 - Alpha
Classifier: Intended Audience :: Developers
Classifier: License :: OSI Approved :: BSD License
Classifier: Programming Language :: Python :: 3.5
Classifier: Programming Language :: Python :: 3.6
Classifier: Programming Language :: Python :: 3.7
Classifier: Programming Language :: Python :: 3.8
Requires-Python: >= 3.5
